CHANGES
CONTRIBUTORS.txt
LICENSE
README.txt
TODO.txt
bootstrap.py
buildout.cfg
setup.cfg
setup.py
collective/__init__.py
collective.releaser.egg-info/PKG-INFO
collective.releaser.egg-info/SOURCES.txt
collective.releaser.egg-info/dependency_links.txt
collective.releaser.egg-info/entry_points.txt
collective.releaser.egg-info/namespace_packages.txt
collective.releaser.egg-info/not-zip-safe
collective.releaser.egg-info/requires.txt
collective.releaser.egg-info/top_level.txt
collective/releaser/README.txt
collective/releaser/__init__.py
collective/releaser/base.py
collective/releaser/bootstrap.py
collective/releaser/config.py
collective/releaser/hook.py
collective/releaser/msgfmt.py
collective/releaser/packet.py
collective/releaser/project.py
collective/releaser/tarfile.py
collective/releaser/templates.py
collective/releaser/testing.py
collective/releaser/commands/__init__.py
collective/releaser/commands/build_mo.py
collective/releaser/commands/extendable.py
collective/releaser/commands/release.py
collective/releaser/templates/releaser_project/backups/README.txt
collective/releaser/templates/releaser_project/buildbot/bootstrap.py
collective/releaser/templates/releaser_project/buildbot/buildout.cfg
collective/releaser/templates/releaser_project/buildbot/master.cfg
collective/releaser/templates/releaser_project/buildbot/slave.cfg
collective/releaser/templates/releaser_project/buildbot/public_html/buildbot.css
collective/releaser/templates/releaser_project/buildout/CHANGES.txt
collective/releaser/templates/releaser_project/buildout/README.txt_tmpl
collective/releaser/templates/releaser_project/buildout/bootstrap.py
collective/releaser/templates/releaser_project/buildout/buildout.cfg_tmpl
collective/releaser/templates/releaser_project/buildout/bin/launch_buildout.bat
collective/releaser/templates/releaser_project/buildout/downloads/README.txt
collective/releaser/templates/releaser_project/bundles/dev/EXTERNALS.txt_tmpl
collective/releaser/templates/releaser_project/docs/README.txt
collective/releaser/templates/releaser_project/docs/architecture.txt
collective/releaser/templates/releaser_project/docs/releasing.txt
collective/releaser/templates/releaser_project/packages/README.txt
collective/releaser/templates/releaser_project/releases/README.txt
collective/releaser/tests/__init__.py
collective/releaser/tests/test_base.py
