Metadata-Version: 1.0
Name: collective.releaser
Version: 0.7.0
Summary: Setuptools extension to release an egg
Home-page: http://pypi.python.org/pypi/collective.releaser
Author: Ingeniweb
Author-email: support@ingeniweb.com
License: GPL
Keywords: egg setuptools extension
Platform: UNKNOWN
Classifier: Programming Language :: Python
Classifier: Topic :: Software Development :: Libraries :: Python Modules
